sync fifo/design.v
// Code your design here

`timescale 1ns/1ps
module fifo(clk,reset,wr_en,rd_en,din,dout,full,empty);
  input clk,reset;
  input wr_en,rd_en;
  input [7:0]din;
  output [7:0]dout;
  output full,empty;
  
  reg [7:0]mem[0:15];//declaration of RAM
  wire clk,reset;
  wire wr_en,rd_en;
  wire [7:0]din;
  reg [7:0]dout;
  wire full,empty;
  reg [4:0]addr;
  integer i;
  assign full = (addr ==5'b10000) ? 1'b1 : 1'b0;
  assign empty = (addr ==5'b00000) ? 1'b1 : 1'b0;
  
  always@(posedge clk)
    begin
      if(reset)
        begin
        	addr = 4'b0000;
      		for(i=0;i<=15;i=i+1) 
        		mem[i] = 8'b0;
        end
      else if(wr_en | rd_en)//read or write
        begin
          if(wr_en && (!full))
            begin
            	mem[addr]=din;
            	addr = addr + 1;
            end
          else
            if(rd_en && (!empty))
              begin
                dout =mem[0];
                mem[0] = mem[1];
                mem[1] = mem[2];
                mem[2] = mem[3];
                mem[3] = mem[4];
                mem[4] = mem[5];
                mem[5] = mem[6];
                mem[6] = mem[7];
                mem[7] = mem[8];
                mem[8] = mem[9];
                mem[9] = mem[10];
                mem[10] = mem[11];
                mem[11] = mem[12];
                mem[12] = mem[13];
                mem[13] = mem[14];
                mem[14] = mem[15];
                mem[15] = 8'b0;
                   addr = addr - 1;         
                
              end
              
        end
      
    end
endmodule

sync fifo/testbench.v
// Code your testbench here
// or browse Examples
`timescale 1ns/1ps
module test_fifo;//no ports
  reg clk,reset;
  reg wr_en,rd_en;
  reg [7:0]din;
  wire [7:0]dout;
  wire full,empty;
  
  fifo UUT(clk,reset,wr_en,rd_en,din,dout,full,empty); //instantiation

  initial begin
    clk =0;
    $display("clock initialize---------------");
      
  end
  
  task rst;
    begin
    #10  reset = 1;
      $display("reset initialize---------------");
    
      #20  reset = 0;//20 ns delay
         end
  endtask
  
  always #5 clk = ~clk;//T=10 ns, f=100Mhz
  
  task wr_rd_init;
    begin
    	wr_en =0;
      	rd_en =0;
      	din = 0;
      $display("write read initialize---------------");
    
    end
  endtask
  
  task write;
    input [7:0]wdata;
    begin
       @(posedge clk)
      begin
        wr_en =  1;
        din =  wdata;
      end
    end
  endtask
  
  task write16;
    begin
      write(8'hff);
      write(8'hfe);
      write(8'hfd);
      write(8'hfc);
      write(8'hfb);
      write(8'hfa);
      write(8'hf9);
      write(8'hf8);
      write(8'hf7);
      write(8'hf6);
      write(8'hf5);
      write(8'hf4);
      write(8'hf3);
      write(8'hf2);
      write(8'hf1);
      write(8'hf0);
      write(8'h11);
      
    end
  endtask
  
  task endwrite;
    begin
      wr_en = 0;
      din =  0;
    end
  endtask
  
  //read process
  task read;
    begin
      @(posedge clk)
      begin
        rd_en = 1;
      end
    end
  endtask
  
  task read16;
    begin
      read;read;read;read;
      read;read;read;read;
      read;read;read;read;
      read;read;read;read;
      
    end
  endtask
  
  task endread;
    begin
       @(posedge clk)
      begin
        rd_en = 0;
      end
    end
  endtask
  
  initial begin
    $display("start--- initialize---------------");
    
    rst;
    wr_rd_init;
    write16;
    endwrite;
    #2 read16;
    #10 endread;
    $display("stopped---------------");
    
    #10 $stop;//Stop the simulation
        
  end
  
  //waveform generation
  initial begin
    $dumpfile("dump.vcd");
    $dumpvars(1,test_fifo);
  end
endmodule

sync fifo/dump.vcd
$date
Tue Aug 27 10:42:38 2024
$end
$version
Riviera-PRO Version 2023.04.112.8911
$end
$timescale
1 ps
$end

$scope module test_fifo $end
$var wire 8 ! dout [7:0] $end
$var wire 1 " full $end
$var wire 1 # empty $end
$var reg 1 $ clk $end
$var reg 1 % reset $end
$var reg 1 & wr_en $end
$var reg 1 ' rd_en $end
$var reg 8 ( din [7:0] $end

$scope task rst $end
$upscope $end


$scope task wr_rd_init $end
$upscope $end


$scope task write $end
$var reg 8 ) wdata [7:0] $end
$upscope $end


$scope task write16 $end
$upscope $end


$scope task endwrite $end
$upscope $end


$scope task read $end
$upscope $end


$scope task read16 $end
$upscope $end


$scope task endread $end
$upscope $end

$upscope $end

$enddefinitions $end
$dumpvars
bx !
x"
x#
0$
x%
x&
x'
bx (
bx )
$end
#5000
1$
#10000
1%
0$
#15000
1$
1#
0"
#20000
0$
#25000
1$
#30000
0%
0&
0'
b0 (
b11111111 )
0$
#35000
1$
1&
b11111111 (
b11111110 )
#40000
0$
#45000
1$
b11111110 (
b11111101 )
0#
#50000
0$
#55000
1$
b11111101 (
b11111100 )
#60000
0$
#65000
1$
b11111100 (
b11111011 )
#70000
0$
#75000
1$
b11111011 (
b11111010 )
#80000
0$
#85000
1$
b11111010 (
b11111001 )
#90000
0$
#95000
1$
b11111001 (
b11111000 )
#100000
0$
#105000
1$
b11111000 (
b11110111 )
#110000
0$
#115000
1$
b11110111 (
b11110110 )
#120000
0$
#125000
1$
b11110110 (
b11110101 )
#130000
0$
#135000
1$
b11110101 (
b11110100 )
#140000
0$
#145000
1$
b11110100 (
b11110011 )
#150000
0$
#155000
1$
b11110011 (
b11110010 )
#160000
0$
#165000
1$
b11110010 (
b11110001 )
#170000
0$
#175000
1$
b11110001 (
b11110000 )
#180000
0$
#185000
1$
b11110000 (
b10001 )
#190000
0$
#195000
1$
b0 (
0&
1"
#200000
0$
#205000
1$
1'
#210000
0$
#215000
1$
0"
b11111111 !
#220000
0$
#225000
1$
b11111110 !
#230000
0$
#235000
1$
b11111101 !
#240000
0$
#245000
1$
b11111100 !
#250000
0$
#255000
1$
b11111011 !
#260000
0$
#265000
1$
b11111010 !
#270000
0$
#275000
1$
b11111001 !
#280000
0$
#285000
1$
b11111000 !
#290000
0$
#295000
1$
b11110111 !
#300000
0$
#305000
1$
b11110110 !
#310000
0$
#315000
1$
b11110101 !
#320000
0$
#325000
1$
b11110100 !
#330000
0$
#335000
1$
b11110011 !
#340000
0$
#345000
1$
b11110010 !
#350000
0$
#355000
1$
b11110001 !
#360000
0$
#365000
1$
0'
1#
b11110000 !
