async fifo/design.v
// Code your design here
module asyncfifo(
                write_clk,
                read_clk ,//input clk
                reset,    //input reset
                write_en,//input write enable
                read_en,//input read enable
                data_in,//input data
                full,//output if the memory is full 
                empty,//output if the memory is 
  				out//output out
                );

//port declarations
input            write_clk,read_clk,reset,write_en,read_en;
input      [7:0] data_in;
output           full,empty;
output reg [7:0] out;

//reg declarations
reg [7:0] memory_vec   [0:7];//memory of 8 * 8 
reg [3:0] write_pointer;//write pointer
reg [3:0] read_pointer;//read pointer;
  

assign full  = (write_pointer[3]==1 && read_pointer[3]==0 && write_pointer[2:0]==read_pointer[2:0]);//assign full to 8
assign empty = (write_pointer ==read_pointer);


always @ (posedge write_clk or negedge reset)
   begin
      if(!reset)
         begin
            write_pointer <= 4'b0;//reset write pointer
         end
      else
         begin
            if(write_en == 1 && !full)
               begin
                  memory_vec   [write_pointer[2:0]] <=  data_in ;//data is written to the location
                  write_pointer <=  write_pointer + 1'b1 ;//increment pointer
               end
         end
    end


always @ (posedge read_clk or negedge reset)
   begin
      if(!reset)
         begin
            read_pointer <= 4'b0  ;//reset read pointer
         end
      else
         begin
            if(read_en == 1 && !empty)
               begin
                  out  <=  memory_vec[read_pointer[2:0]];//data is read from the pointer location
                  read_pointer <=  read_pointer + 1'b1;//increment read pointer
               end
         end
    end
endmodule

async fifo/testbench.v
// Code your testbench here
// or browse Examples
module asyncfifo_tb ;//testbench module
reg        write_clk, read_clk, reset, write_en, read_en;//register declaration 
reg  [7:0] data_in;
wire       mem_full, mem_empty;
wire [7:0] out;

//instantiation of design module
asyncfifo dut(
             .write_clk (write_clk) ,//input write clock
             .read_clk  (read_clk )  ,//input read clock
             .reset     (reset    )  ,//input reset
             .write_en  (write_en )          ,//write enable
             .read_en   (read_en  )          ,//read enable 
             .data_in   (data_in  )          ,//data input
             .full  (mem_full )          ,//memory full
             .empty (mem_empty)          ,//memory empty 
             .out       (out      )           //output
            )                                ;

//generates clock for write operation 
initial begin

   write_clk            = 1'b0               ;
   forever #5 write_clk = ~write_clk         ;
end

//generates clock for read operation 
initial begin
   read_clk             = 1'b0               ;
   forever #10 read_clk = ~read_clk          ;
end

//calling the write and read operations
initial begin
$dumpfile ("asyncfifo_tb.vcd") ;
    $dumpvars (0, asyncfifo_tb) ;
   reset      = 1'b1                         ;
   write_en   = 1'b0                         ;
   read_en    = 1'b0                         ;
   data_in    = 8'b0                         ;#10;
   reset      = 1'b0                         ;#10;
   reset      = 1'b1                         ;
   
   write_task                                ;#20;//calling the task write
   read_task                                 ;#20;//calling the task read
   write_task;#20                            ;
   write_task                                ;
   #200 $finish                              ;//finish simulation
end

task write_task                              ;//task
   begin
      write_en    = 1'b1                     ;
      read_en     = 1'b0                     ;
      data_in     = $random                  ;#20;
      $display("write_en = %b , read_en = %b , data_in = %b , out = %b , mem_full = %b , mem_empty = %b",write_en,read_en,data_in,out,mem_full,mem_empty);//display statement
   end
endtask

task read_task                               ;//task
   begin
      write_en   = 1'b0                      ;
      read_en    = 1'b1                      ;#20;
      $display("write_en = %b , read_en = %b , data_in = %b , out = %b , mem_full = %b , mem_empty = %b",write_en,read_en,data_in,out,mem_full,mem_empty);//display statement
   end
endtask 

endmodule                                     //end of testbench

async fifo/asyncfifo_tb.vcd
$date
Tue Aug 27 10:47:24 2024
$end
$version
Riviera-PRO Version 2023.04.112.8911
$end
$timescale
1 ns
$end

$scope module asyncfifo_tb $end
$var wire 1 ! mem_full $end
$var wire 1 " mem_empty $end
$var wire 8 # out [7:0] $end
$var reg 1 $ write_clk $end
$var reg 1 % read_clk $end
$var reg 1 & reset $end
$var reg 1 ' write_en $end
$var reg 1 ( read_en $end
$var reg 8 ) data_in [7:0] $end

$scope module dut $end
$var wire 1 * write_clk $end
$var wire 1 + read_clk $end
$var wire 1 , reset $end
$var wire 1 - write_en $end
$var wire 1 . read_en $end
$var wire 8 / data_in [7:0] $end
$var wire 1 ! full $end
$var wire 1 " empty $end
$var reg 8 0 out [7:0] $end
$var reg 4 1 write_pointer [3:0] $end
$var reg 4 2 read_pointer [3:0] $end
$upscope $end


$scope task write_task $end
$upscope $end


$scope task read_task $end
$upscope $end

$upscope $end

$enddefinitions $end
$dumpvars
x!
x"
bx #
0$
0%
1&
0'
0(
b0 )
0*
0+
1,
0-
0.
b0 /
bx 0
bx 1
bx 2
$end
#5
1$
1*
#10
1%
0&
0$
0*
0,
1+
b0 1
b0 2
1"
0!
#15
1$
1*
#20
0%
1&
1'
b100100 )
0$
0*
b100100 /
1-
1,
0+
#25
1$
1*
b1 1
0"
#30
1%
0$
0*
1+
#35
1$
1*
b10 1
#40
0%
0$
0*
0+
#45
1$
1*
b11 1
#50
1%
0$
0*
1+
#55
1$
1*
b100 1
#60
0'
1(
0%
0$
0*
0+
1.
0-
#65
1$
1*
#70
1%
0$
0*
1+
b100100 0
b1 2
b100100 #
#75
1$
1*
#80
0%
0$
0*
0+
#85
1$
1*
#90
1%
0$
0*
1+
b10 2
#95
1$
1*
#100
1'
0(
b10000001 )
0%
0$
0*
0+
b10000001 /
0.
1-
#105
1$
1*
b101 1
#110
1%
0$
0*
1+
#115
1$
1*
b110 1
#120
0%
0$
0*
0+
#125
1$
1*
b111 1
#130
1%
0$
0*
1+
#135
1$
1*
b1000 1
#140
b1001 )
0%
0$
0*
0+
b1001 /
#145
1$
1*
b1001 1
#150
1%
0$
0*
1+
#155
1$
1*
b1010 1
1!
